[{"course":"SE2250","name":"Clarita Aymerich","email":"caymerich0@imgur.com","status":1,"questions":[{"question":"Know Python?","answer":true},{"question":"Know DBMS?","answer":false},{"question":"Know Matlab?","answer":false},{"question":"Know OOP?","answer":false},{"question":"Know Matlab?","answer":false}]},
{"course":"SE2202","name":"Lisbeth Finlow","email":"lfinlow1@live.com","status":1,"questions":[{"question":"Know DBMS?","answer":false},{"question":"Teaching Certificate?","answer":true},{"question":"Question","answer":false},{"question":"Question","answer":true}]},
{"course":"SE3310","name":"Augusto Mor","email":"amor2@nsw.gov.au","status":2,"questions":[{"question":"Know Matlab?","answer":false},{"question":"Teaching Certificate?","answer":true},{"question":"Question","answer":false},{"question":"Know Matlab?","answer":false},{"question":"Question","answer":false}]},
{"course":"SE3314","name":"Natalie Heistermann","email":"nheistermann3@latimes.com","status":1,"questions":[{"question":"Know Matlab?","answer":true},{"question":"Know OOP?","answer":true}]},
{"course":"SE3316","name":"Red Brooksbie","email":"rbrooksbie4@delicious.com","status":2,"questions":[{"question":"Know Python?","answer":false},{"question":"Know Python?","answer":false}]},
{"course":"SE2202","name":"Averell Klemz","email":"aklemz5@xing.com","status":2,"questions":[{"question":"Teaching Certificate?","answer":true},{"question":"Know Matlab?","answer":true},{"question":"Teaching Certificate?","answer":false},{"question":"Know Python?","answer":true}]},
{"course":"SE3316","name":"Aubree Custed","email":"acusted6@google.pl","status":2,"questions":[{"question":"Teaching Certificate?","answer":true},{"question":"Question","answer":true},{"question":"Know OOP?","answer":true},{"question":"Know Python?","answer":true}]},
{"course":"SE3314","name":"Desirae Wilkison","email":"dwilkison7@parallels.com","status":3,"questions":[{"question":"Know C++?","answer":true},{"question":"Know Matlab?","answer":false},{"question":"Know Matlab?","answer":true}]},
{"course":"SE2250","name":"Roxi Kime","email":"rkime8@npr.org","status":1,"questions":[{"question":"Know Matlab?","answer":false},{"question":"Know DBMS?","answer":true},{"question":"Question","answer":false},{"question":"Know Python?","answer":true}]},
{"course":"SE3313","name":"Ced Chaffey","email":"cchaffey9@stumbleupon.com","status":3,"questions":[{"question":"Know OOP?","answer":true},{"question":"Know C++?","answer":false}]},
{"course":"SE3309","name":"Etienne Ofield","email":"eofielda@nasa.gov","status":1,"questions":[{"question":"Know C++?","answer":true},{"question":"Question","answer":true},{"question":"Know Matlab?","answer":false},{"question":"Know OOP?","answer":false}]},
{"course":"SE2250","name":"Jacquette O'Dunniom","email":"jodunniomb@go.com","status":1,"questions":[{"question":"Teaching Certificate?","answer":true},{"question":"Know C++?","answer":false},{"question":"Know Java?","answer":false},{"question":"Know Java?","answer":false},{"question":"Know Matlab?","answer":true}]},
{"course":"SE2202","name":"Zolly Burds","email":"zburdsc@wikia.com","status":1,"questions":[{"question":"Know DBMS?","answer":false}]},
{"course":"SE3350","name":"Cristine Salter","email":"csalterd@blogs.com","status":3,"questions":[{"question":"Know Python?","answer":false}]},
{"course":"SE2205","name":"Carly Besant","email":"cbesante@cloudflare.com","status":1,"questions":[{"question":"Know Matlab?","answer":true},{"question":"Know Python?","answer":true},{"question":"Teaching Certificate?","answer":false}]},
{"course":"SE3316","name":"Ximenes Loynes","email":"xloynesf@geocities.com","status":2,"questions":[{"question":"Know DBMS?","answer":true},{"question":"Know DBMS?","answer":false},{"question":"Know Java?","answer":true},{"question":"Know Matlab?","answer":false},{"question":"Teaching Certificate?","answer":true}]},
{"course":"SE2202","name":"Lanny Heindl","email":"lheindlg@pen.io","status":3,"questions":[{"question":"Know C++?","answer":true},{"question":"Know Python?","answer":true},{"question":"Know DBMS?","answer":true}]},
{"course":"SE3314","name":"Ferne Idale","email":"fidaleh@yandex.ru","status":2,"questions":[{"question":"Know OOP?","answer":true}]},
{"course":"SE3313","name":"Nan Sheringham","email":"nsheringhami@fda.gov","status":2,"questions":[{"question":"Question","answer":false},{"question":"Know C++?","answer":true},{"question":"Teaching Certificate?","answer":true}]},
{"course":"SE3309","name":"Orv Hincham","email":"ohinchamj@go.com","status":2,"questions":[{"question":"Know C++?","answer":true},{"question":"Know Matlab?","answer":false}]},
{"course":"SE2202","name":"Angelita Laurenty","email":"alaurentyk@wiley.com","status":3,"questions":[{"question":"Know OOP?","answer":false},{"question":"Know C++?","answer":true},{"question":"Know Python?","answer":false},{"question":"Know Java?","answer":false}]},
{"course":"SE2203","name":"Costanza Copin","email":"ccopinl@imgur.com","status":3,"questions":[{"question":"Know Python?","answer":true},{"question":"Know OOP?","answer":true},{"question":"Know Python?","answer":true}]},
{"course":"SE3316","name":"Mallorie Madgewick","email":"mmadgewickm@hexun.com","status":2,"questions":[{"question":"Know C++?","answer":true},{"question":"Teaching Certificate?","answer":true}]},
{"course":"SE3314","name":"Patsy Baillie","email":"pbaillien@oakley.com","status":2,"questions":[{"question":"Know Python?","answer":true},{"question":"Know OOP?","answer":false}]},
{"course":"SE3350","name":"Leonid Kirtley","email":"lkirtleyo@devhub.com","status":2,"questions":[{"question":"Question","answer":false},{"question":"Know Matlab?","answer":true}]},
{"course":"SE2203","name":"Gregor Storks","email":"gstorksp@shutterfly.com","status":1,"questions":[{"question":"Know C++?","answer":false},{"question":"Know C++?","answer":true},{"question":"Know Matlab?","answer":true},{"question":"Know Python?","answer":false}]},
{"course":"SE3309","name":"Mart Davoren","email":"mdavorenq@free.fr","status":1,"questions":[{"question":"Know Matlab?","answer":true},{"question":"Know Java?","answer":true},{"question":"Know Matlab?","answer":false},{"question":"Teaching Certificate?","answer":true}]},
{"course":"SE2202","name":"Catie Phair","email":"cphairr@wp.com","status":2,"questions":[{"question":"Know OOP?","answer":true},{"question":"Know Matlab?","answer":true},{"question":"Know DBMS?","answer":false},{"question":"Know Java?","answer":true},{"question":"Question","answer":true}]},
{"course":"SE3314","name":"Phaidra Tellenbrook","email":"ptellenbrooks@paypal.com","status":3,"questions":[{"question":"Know C++?","answer":true},{"question":"Know Python?","answer":true},{"question":"Know Python?","answer":false},{"question":"Know DBMS?","answer":false},{"question":"Know Matlab?","answer":false}]},
{"course":"SE3316","name":"Howie Kingswood","email":"hkingswoodt@dagondesign.com","status":2,"questions":[{"question":"Know Python?","answer":false}]},
{"course":"SE3350","name":"Abbie McEwen","email":"amcewenu@arizona.edu","status":1,"questions":[{"question":"Question","answer":true},{"question":"Know C++?","answer":false},{"question":"Know OOP?","answer":false},{"question":"Know C++?","answer":true},{"question":"Know OOP?","answer":false}]},
{"course":"SE3314","name":"Rinaldo Mation","email":"rmationv@slate.com","status":2,"questions":[{"question":"Know OOP?","answer":false},{"question":"Know Matlab?","answer":false},{"question":"Know Java?","answer":true},{"question":"Question","answer":false},{"question":"Know C++?","answer":false}]},
{"course":"SE3310","name":"Ninon Feares","email":"nfearesw@kickstarter.com","status":2,"questions":[{"question":"Know DBMS?","answer":false},{"question":"Know Matlab?","answer":false},{"question":"Know DBMS?","answer":false},{"question":"Teaching Certificate?","answer":true},{"question":"Question","answer":true}]},
{"course":"SE3309","name":"Goldi Vise","email":"gvisex@jimdo.com","status":2,"questions":[{"question":"Know Java?","answer":true},{"question":"Know Java?","answer":false},{"question":"Question","answer":true},{"question":"Know C++?","answer":false},{"question":"Question","answer":false}]},
{"course":"SE2250","name":"Rachel Proudler","email":"rproudlery@sphinn.com","status":2,"questions":[{"question":"Know C++?","answer":false},{"question":"Know Matlab?","answer":true},{"question":"Know Java?","answer":false}]},
{"course":"SE3350","name":"Billie Priddey","email":"bpriddeyz@businesswire.com","status":2,"questions":[{"question":"Know DBMS?","answer":false},{"question":"Question","answer":true}]},
{"course":"SE3309","name":"Kali Lush","email":"klush10@oakley.com","status":3,"questions":[{"question":"Know Java?","answer":true},{"question":"Know OOP?","answer":false}]},
{"course":"SE3316","name":"Alwin Shutle","email":"ashutle11@engadget.com","status":2,"questions":[{"question":"Know OOP?","answer":true},{"question":"Know DBMS?","answer":true},{"question":"Know Matlab?","answer":false},{"question":"Know Java?","answer":true}]},
{"course":"SE2203","name":"Malynda Lemm","email":"mlemm12@go.com","status":2,"questions":[{"question":"Know OOP?","answer":true},{"question":"Know Matlab?","answer":true},{"question":"Know DBMS?","answer":false}]},
{"course":"SE2202","name":"Jae Blofeld","email":"jblofeld13@fema.gov","status":1,"questions":[{"question":"Know OOP?","answer":false},{"question":"Question","answer":false},{"question":"Know Python?","answer":true},{"question":"Know Python?","answer":true}]},
{"course":"SE2205","name":"Dyna Kubik","email":"dkubik14@wufoo.com","status":2,"questions":[{"question":"Know DBMS?","answer":false}]},
{"course":"SE2202","name":"Monroe Scarman","email":"mscarman15@washingtonpost.com","status":1,"questions":[{"question":"Know Matlab?","answer":true},{"question":"Know Matlab?","answer":true},{"question":"Teaching Certificate?","answer":false},{"question":"Know Matlab?","answer":true}]},
{"course":"SE2203","name":"Darill Pensom","email":"dpensom16@cloudflare.com","status":1,"questions":[{"question":"Know DBMS?","answer":false},{"question":"Know OOP?","answer":false},{"question":"Know Java?","answer":true},{"question":"Know Python?","answer":true},{"question":"Know Java?","answer":false}]},
{"course":"SE3314","name":"Sheff Cofax","email":"scofax17@dagondesign.com","status":3,"questions":[{"question":"Know Java?","answer":true},{"question":"Know OOP?","answer":true},{"question":"Question","answer":true},{"question":"Know Java?","answer":true},{"question":"Know Python?","answer":true}]},
{"course":"SE3314","name":"West Kinsley","email":"wkinsley18@scribd.com","status":3,"questions":[{"question":"Question","answer":true},{"question":"Know Python?","answer":true},{"question":"Know C++?","answer":true},{"question":"Question","answer":false}]},
{"course":"SE3310","name":"Cord Lynch","email":"clynch19@pcworld.com","status":2,"questions":[{"question":"Question","answer":true},{"question":"Know DBMS?","answer":true},{"question":"Know Matlab?","answer":false},{"question":"Know DBMS?","answer":true}]},
{"course":"SE3350","name":"Alethea Catonne","email":"acatonne1a@qq.com","status":3,"questions":[{"question":"Know Python?","answer":true},{"question":"Know OOP?","answer":false}]},
{"course":"SE3314","name":"Wells Bartomieu","email":"wbartomieu1b@jalbum.net","status":3,"questions":[{"question":"Teaching Certificate?","answer":false},{"question":"Know Java?","answer":false}]},
{"course":"SE2250","name":"Persis Widdall","email":"pwiddall1c@china.com.cn","status":3,"questions":[{"question":"Know OOP?","answer":true},{"question":"Know Matlab?","answer":true}]},
{"course":"SE3313","name":"Shel Dolling","email":"sdolling1d@google.fr","status":1,"questions":[{"question":"Know Java?","answer":true},{"question":"Question","answer":true}]}]